{"type":"FeatureCollection","features":[
{"type":"Feature","geometry":{"type":"Point","coordinates":[36.69965744,-3.3910409]},"properties":{"Country":"Tanzania","FormalCountryName":"United Republic of Tanzania","CountrySort":"Tanzania","AfricaRegion":"Eastern Africa","Description":"Radio coverage plot 1","TX":"2.5 KW FM w/ 4 bay antenna","RX":"Custom","Frequency":"103 MHz","Base Name":"Radio 5","Latitude":"03° 23' 27.75\"S","Longitude":"036° 41' 58.77\"E","UTM (WGS84)":"37M E244406 S9624880","Elevation":"1450.5","Base Ant. Height":"60","Base Ant. Gain":"5.4","Mobile Ant. Height":"3.0 m","Tx Power":"2500","Tx Line Loss":"0.4","Weak signal field":"48.0 dBμV/m","Strong signal field":"60.0 dBμV/m","Weak signal covered area":"11362 km2","Strong signal covered area":"6122 km2","Weak signal population reached":"1025217 pop","Strong signal population reached":"615877 pop","Landcover used":"Yes","Two rays method used":"No","User ID":"farmradio","Radio coverage ID":"NAUTEL7B7A4EC0895_1","Generated on":"8/9/2016 10:18:28 PM","ISO_A3":"TZA","desc":null,"group":null,"zoom":null,"stationname":null}},
{"type":"Feature","geometry":{"type":"Point","coordinates":[32.912556,-2.484889]},"properties":{"Country":"Tanzania","FormalCountryName":"United Republic of Tanzania","CountrySort":"Tanzania","AfricaRegion":"Eastern Africa","Description":"RFA Mwanza","TX":"1 KW FM w/ 4 bay antenna","RX":"Custom","Frequency":"89.8 MHz","Base Name":"RFA - Mwanza","Latitude":"02° 29' 05.60\"S","Longitude":"032° 54' 45.20\"E","UTM (WGS84)":"36M E490279 S9725343","Elevation":"1260.2","Base Ant. Height":"108","Base Ant. Gain":"5.4","Mobile Ant. Height":"5.0 m","Tx Power":"1000","Tx Line Loss":"1.3","Weak signal field":"48.0 dBμV/m","Strong signal field":"60.0 dBμV/m","Weak signal covered area":"9243 km2","Strong signal covered area":"3975 km2","Weak signal population reached":"918004 pop","Strong signal population reached":"555410 pop","Landcover used":"Yes","Two rays method used":"No","User ID":"farmradio","Radio coverage ID":"NAUTEL37752192A206_1","Generated on":"8/9/2016 10:19:40 PM","ISO_A3":"TZA","desc":"","group":"","zoom":10,"stationname":"RFA - Mwanza"}},
{"type":"Feature","geometry":{"type":"Point","coordinates":[33.80425,-1.494033]},"properties":{"Country":"Tanzania","FormalCountryName":"United Republic of Tanzania","CountrySort":"Tanzania","AfricaRegion":"Eastern Africa","Description":"RFA - Musoma","TX":"1 KW FM w/ 4 bay antenna","RX":"Custom","Frequency":"93.5 MHz","Base Name":"RFA - Musoma","Latitude":"01° 29' 38.52\"S","Longitude":"033° 48' 15.30\"E","UTM (WGS84)":"36M E589466 S9834848","Elevation":"1190","Base Ant. Height":"100","Base Ant. Gain":"5.4","Mobile Ant. Height":"5.0 m","Tx Power":"1000","Tx Line Loss":"1.2","Weak signal field":"48.0 dBμV/m","Strong signal field":"60.0 dBμV/m","Weak signal covered area":"6614 km2","Strong signal covered area":"2277 km2","Weak signal population reached":"483500 pop","Strong signal population reached":"285620 pop","Landcover used":"Yes","Two rays method used":"No","User ID":"farmradio","Radio coverage ID":"NAUTEL85B8E2544BB_1","Generated on":"8/9/2016 10:19:46 PM","ISO_A3":"TZA","desc":"","group":"","zoom":15,"stationname":"RFA - Musoma"}},
{"type":"Feature","geometry":{"type":"Point","coordinates":[33.416667,-3.666667]},"properties":{"Country":"Tanzania","FormalCountryName":"United Republic of Tanzania","CountrySort":"Tanzania","AfricaRegion":"Eastern Africa","Description":"RFA - Shinyanga","TX":"1 KW FM w/ 4 bay antenna","RX":"Custom","Frequency":"88.2 MHz","Base Name":"RFA - Shinyanga","Latitude":"03° 40' 00.00\"S","Longitude":"033° 25' 00.00\"E","UTM (WGS84)":"36M E546271 S9594707","Elevation":"1139","Base Ant. Height":"100","Base Ant. Gain":"5.4","Mobile Ant. Height":"5.0 m","Tx Power":"1000","Tx Line Loss":"1.2","Weak signal field":"48.0 dBμV/m","Strong signal field":"60.0 dBμV/m","Weak signal covered area":"5337 km2","Strong signal covered area":"1935 km2","Weak signal population reached":"453316 pop","Strong signal population reached":"224066 pop","Landcover used":"Yes","Two rays method used":"No","User ID":"farmradio","Radio coverage ID":"NAUTEL85B8E2544BB_2","Generated on":"8/9/2016 10:19:49 PM","ISO_A3":"TZA","desc":"","group":"","zoom":14,"stationname":"RFA - Shinyanga"}},
{"type":"Feature","geometry":{"type":"Point","coordinates":[37.59279022,-6.83397643]},"properties":{"Country":"Tanzania","FormalCountryName":"United Republic of Tanzania","CountrySort":"Tanzania","AfricaRegion":"Eastern Africa","Description":"Radio 5 - Morogoro coverage plot","TX":"2 KW","RX":"FM Car Receiver","Frequency":"95.1 MHz","Base Name":"Radio 5 (Morogoro)","Latitude":"06° 50' 02.32\"S","Longitude":"037° 35' 34.04\"E","UTM (WGS84)":"37M E344503 S9244377","Elevation":"1148","Base Ant. Height":"70","Base Ant. Gain":"2.1","Mobile Ant. Height":"1.0 m","Tx Power":"2000","Tx Line Loss":"0.3","Weak signal field":"33.3 dBμV/m","Strong signal field":"43.3 dBμV/m","Weak signal covered area":"24964 km2","Strong signal covered area":"12972 km2","Weak signal population reached":"1071664 pop","Strong signal population reached":"620290 pop","Landcover used":"Yes","Two rays method used":"No","User ID":"farmradio","Radio coverage ID":"NAUTEL18E25544771_1","Generated on":"8/9/2016 10:19:51 PM","ISO_A3":"TZA","desc":"","group":"TZ","zoom":11,"stationname":"Radio 5 (Morogoro)"}},
{"type":"Feature","geometry":{"type":"Point","coordinates":[39.1,-5.07]},"properties":{"Country":"Tanzania","FormalCountryName":"United Republic of Tanzania","CountrySort":"Tanzania","AfricaRegion":"Eastern Africa","Description":"Radio 5 -Tanga coverage plot","TX":"1 KW FM w/ 4 bay antenna","RX":"Custom","Frequency":"98.9 MHz","Base Name":"Radio 5 (Tanga)","Latitude":"05° 04' 12.00\"S","Longitude":"039° 06' 00.00\"E","UTM (WGS84)":"37M E511084 S9439597","Elevation":"29","Base Ant. Height":"65","Base Ant. Gain":"5.4","Mobile Ant. Height":"5.0 m","Tx Power":"1000","Tx Line Loss":"0.8","Weak signal field":"48.0 dBμV/m","Strong signal field":"60.0 dBμV/m","Weak signal covered area":"38283 km2","Strong signal covered area":"21436 km2","Weak signal population reached":"1783701 pop","Strong signal population reached":"1255010 pop","Landcover used":"Yes","Two rays method used":"No","User ID":"farmradio","Radio coverage ID":"NAUTELCF9655A1BD4_3","Generated on":"8/9/2016 10:19:53 PM","ISO_A3":"TZA","desc":"This is Radio 5 Transmitter in Tanga ","group":"TZ","zoom":8,"stationname":"Radio 5 (Tanga)"}},
{"type":"Feature","geometry":{"type":"Point","coordinates":[33.45025749,-8.95025435]},"properties":{"Country":"Tanzania","FormalCountryName":"United Republic of Tanzania","CountrySort":"Tanzania","AfricaRegion":"Eastern Africa","Description":"Radio 5 - Mbeya coverage plot","TX":"2 KW","RX":"Custom","Frequency":"93.8 MHz","Base Name":"Radio 5 (Mbeya)","Latitude":"08° 57' 00.92\"S","Longitude":"033° 27' 00.93\"E","UTM (WGS84)":"36L E549497 S9010617","Elevation":"1651.9","Base Ant. Height":"70","Base Ant. Gain":"4.8","Mobile Ant. Height":"5.0 m","Tx Power":"2000","Tx Line Loss":"0.3","Weak signal field":"48.0 dBμV/m","Strong signal field":"60.0 dBμV/m","Weak signal covered area":"1888 km2","Strong signal covered area":"798 km2","Weak signal population reached":"316472 pop","Strong signal population reached":"253402 pop","Landcover used":"Yes","Two rays method used":"No","User ID":"farmradio","Radio coverage ID":"NAUTELAE8771D9AA28_1","Generated on":"8/9/2016 10:19:56 PM","ISO_A3":"TZA","desc":"This is Radio 5 Transmitter in Mbeya","group":"TZ","zoom":15,"stationname":"Radio 5 (Mbeya)"}},
{"type":"Feature","geometry":{"type":"Point","coordinates":[33.45025749,-8.95025435]},"properties":{"Country":"Tanzania","FormalCountryName":"United Republic of Tanzania","CountrySort":"Tanzania","AfricaRegion":"Eastern Africa","Description":"Radio 5 - Mbeya coverage plot","TX":"2 KW","RX":"Custom","Frequency":"93.8 MHz","Base Name":"Radio 5 (Mbeya)","Latitude":"08° 57' 00.92\"S","Longitude":"033° 27' 00.93\"E","UTM (WGS84)":"36L E549497 S9010617","Elevation":"1651.9","Base Ant. Height":"70","Base Ant. Gain":"4.8","Mobile Ant. Height":"5.0 m","Tx Power":"2000","Tx Line Loss":"0.3","Weak signal field":"48.0 dBμV/m","Strong signal field":"60.0 dBμV/m","Weak signal covered area":"1888 km2","Strong signal covered area":"798 km2","Weak signal population reached":"316472 pop","Strong signal population reached":"253402 pop","Landcover used":"Yes","Two rays method used":"No","User ID":"farmradio","Radio coverage ID":"NAUTELAE8771D9AA28_1","Generated on":"8/9/2016 10:19:56 PM","ISO_A3":"TZA","desc":"This is Radio 5 Transmitter in Mbeya","group":"TZ","zoom":15,"stationname":"Radio 5 (Mbeya)"}},
{"type":"Feature","geometry":{"type":"Point","coordinates":[32.71430254,-2.68804593]},"properties":{"Country":"Tanzania","FormalCountryName":"United Republic of Tanzania","CountrySort":"Tanzania","AfricaRegion":"Eastern Africa","Description":"Radio Sengerama coverage plot","TX":"1 KW FM w/ 4 bay antenna","RX":"Custom","Frequency":"98.8 MHz","Base Name":"Radio Sengerema Shinyanga","Latitude":"02° 41' 16.97\"S","Longitude":"032° 42' 51.49\"E","UTM (WGS84)":"36M E468244 S9702884","Elevation":"1324","Base Ant. Height":"70","Base Ant. Gain":"5.4","Mobile Ant. Height":"5.0 m","Tx Power":"1000","Tx Line Loss":"0.9","Weak signal field":"48.0 dBμV/m","Strong signal field":"60.0 dBμV/m","Weak signal covered area":"8653 km2","Strong signal covered area":"3961 km2","Weak signal population reached":"1070241 pop","Strong signal population reached":"538603 pop","Landcover used":"Yes","Two rays method used":"No","User ID":"farmradio","Radio coverage ID":"NAUTELB48D814E2FA0_6","Generated on":"8/9/2016 10:20:02 PM","ISO_A3":"TZA","desc":"This is the transmitter for Radio Sengerema Shinyanga","group":"TZ","zoom":15,"stationname":"Radio Sengerema Shinyanga"}},
{"type":"Feature","geometry":{"type":"Point","coordinates":[33.80425,-1.494033]},"properties":{"Country":"Tanzania","FormalCountryName":"United Republic of Tanzania","CountrySort":"Tanzania","AfricaRegion":"Eastern Africa","Description":"RFA Musoma coverage plot","TX":"1 KW FM w/ 4 bay antenna","RX":"Custom","Frequency":"93.5 MHz","Base Name":"RFA - Musoma","Latitude":"01° 29' 38.52\"S","Longitude":"033° 48' 15.30\"E","UTM (WGS84)":"36M E589466 S9834848","Elevation":"1190","Base Ant. Height":"100","Base Ant. Gain":"5.4","Mobile Ant. Height":"5.0 m","Tx Power":"1000","Tx Line Loss":"1.2","Weak signal field":"48.0 dBμV/m","Strong signal field":"60.0 dBμV/m","Weak signal covered area":"7239 km2","Strong signal covered area":"2518 km2","Weak signal population reached":"502998 pop","Strong signal population reached":"290195 pop","Landcover used":"Yes","Two rays method used":"No","User ID":"farmradio","Radio coverage ID":"NAUTELB48D814E2FA0_7","Generated on":"8/9/2016 10:20:03 PM","ISO_A3":"TZA","desc":"","group":"","zoom":15,"stationname":"RFA - Musoma"}},
{"type":"Feature","geometry":{"type":"Point","coordinates":[32.912556,-2.484889]},"properties":{"Country":"Tanzania","FormalCountryName":"United Republic of Tanzania","CountrySort":"Tanzania","AfricaRegion":"Eastern Africa","Description":"RFA Mwanza coverage plot","TX":"1 KW FM w/ 4 bay antenna","RX":"Custom","Frequency":"89.8 MHz","Base Name":"RFA - Mwanza","Latitude":"02° 29' 05.60\"S","Longitude":"032° 54' 45.20\"E","UTM (WGS84)":"36M E490279 S9725343","Elevation":"1260.2","Base Ant. Height":"108","Base Ant. Gain":"5.4","Mobile Ant. Height":"5.0 m","Tx Power":"1000","Tx Line Loss":"1.3","Weak signal field":"48.0 dBμV/m","Strong signal field":"60.0 dBμV/m","Weak signal covered area":"9805 km2","Strong signal covered area":"4313 km2","Weak signal population reached":"990490 pop","Strong signal population reached":"581909 pop","Landcover used":"Yes","Two rays method used":"No","User ID":"farmradio","Radio coverage ID":"NAUTELB48D814E2FA0_8","Generated on":"8/9/2016 10:20:05 PM","ISO_A3":"TZA","desc":"","group":"","zoom":10,"stationname":"RFA - Mwanza"}},
{"type":"Feature","geometry":{"type":"Point","coordinates":[33.416667,-3.666667]},"properties":{"Country":"Tanzania","FormalCountryName":"United Republic of Tanzania","CountrySort":"Tanzania","AfricaRegion":"Eastern Africa","Description":"RFA Shinyanga coverage plot","TX":"1 KW FM w/ 4 bay antenna","RX":"Custom","Frequency":"88.2 MHz","Base Name":"RFA - Shinyanga","Latitude":"03° 40' 00.00\"S","Longitude":"033° 25' 00.00\"E","UTM (WGS84)":"36M E546271 S9594707","Elevation":"1139","Base Ant. Height":"100","Base Ant. Gain":"5.4","Mobile Ant. Height":"5.0 m","Tx Power":"1000","Tx Line Loss":"1.2","Weak signal field":"48.0 dBμV/m","Strong signal field":"60.0 dBμV/m","Weak signal covered area":"5428 km2","Strong signal covered area":"2125 km2","Weak signal population reached":"472525 pop","Strong signal population reached":"248325 pop","Landcover used":"Yes","Two rays method used":"No","User ID":"farmradio","Radio coverage ID":"NAUTELB48D814E2FA0_9","Generated on":"8/9/2016 10:20:05 PM","ISO_A3":"TZA","desc":"","group":"","zoom":14,"stationname":"RFA - Shinyanga"}},
{"type":"Feature","geometry":{"type":"Point","coordinates":[33.25,-3.35]},"properties":{"Country":"Tanzania","FormalCountryName":"United Republic of Tanzania","CountrySort":"Tanzania","AfricaRegion":"Eastern Africa","Description":"Faraja FM Radio coverage","TX":"2.5 KW FM w/ 4 bay antenna","RX":"Custom","Frequency":"89.8 MHz","Base Name":"Faraja FM Radio","Latitude":"03° 21' 00.00\"S","Longitude":"033° 15' 00.00\"E","UTM (WGS84)":"36M E527772 S9629717","Elevation":"1177","Base Ant. Height":"60","Base Ant. Gain":"5.4","Mobile Ant. Height":"5.0 m","Tx Power":"2500","Tx Line Loss":"0.4","Weak signal field":"48.0 dBμV/m","Strong signal field":"60.0 dBμV/m","Weak signal covered area":"5186 km2","Strong signal covered area":"2040 km2","Weak signal population reached":"507990 pop","Strong signal population reached":"173486 pop","Landcover used":"Yes","Two rays method used":"No","User ID":"farmradio","Radio coverage ID":"NAUTELA94F5342325_1","Generated on":"8/9/2016 10:20:13 PM","ISO_A3":"TZA","desc":"Irish Aid II Shinyanya","group":"Irish_Aid_II_Tz","zoom":16,"stationname":"Faraja FM Radio"}},
{"type":"Feature","geometry":{"type":"Point","coordinates":[39.12338734,-4.77523149]},"properties":{"Country":"Tanzania","FormalCountryName":"United Republic of Tanzania","CountrySort":"Tanzania","AfricaRegion":"Eastern Africa","Description":"Mwambao FM coverage 4 bay","TX":"2.5 KW FM w/ 4 bay antenna","RX":"Custom","Frequency":"106 MHz","Base Name":"Mwambao FM","Latitude":"04° 46' 30.83\"S","Longitude":"039° 07' 24.19\"E","UTM (WGS84)":"37M E513683 S9472180","Elevation":"260.9","Base Ant. Height":"30","Base Ant. Gain":"5.4","Mobile Ant. Height":"5.0 m","Tx Power":"2500","Tx Line Loss":"0.2","Weak signal field":"48.0 dBμV/m","Strong signal field":"60.0 dBμV/m","Weak signal covered area":"15728 km2","Strong signal covered area":"9971 km2","Weak signal population reached":"1062442 pop","Strong signal population reached":"711276 pop","Landcover used":"Yes","Two rays method used":"No","User ID":"farmradio","Radio coverage ID":"NAUTELCD3C95A8D61_1","Generated on":"8/9/2016 10:20:44 PM","ISO_A3":"TZA","desc":"This is the transmitter for Mwambao FM Tanga Tanzania","group":"CIDA3","zoom":13,"stationname":"Mwambao FM"}},
{"type":"Feature","geometry":{"type":"Point","coordinates":[39.12338734,-4.77523149]},"properties":{"Country":"Tanzania","FormalCountryName":"United Republic of Tanzania","CountrySort":"Tanzania","AfricaRegion":"Eastern Africa","Description":"Mwambao FM coverage plot","TX":"2 KW","RX":"Custom","Frequency":"106 MHz","Base Name":"Mwambao FM","Latitude":"04° 46' 30.83\"S","Longitude":"039° 07' 24.19\"E","UTM (WGS84)":"37M E513683 S9472180","Elevation":"260.9","Base Ant. Height":"30","Base Ant. Gain":"3.2","Mobile Ant. Height":"5.0 m","Tx Power":"2000","Tx Line Loss":"0.3","Weak signal field":"48.0 dBμV/m","Strong signal field":"60.0 dBμV/m","Weak signal covered area":"14103 km2","Strong signal covered area":"8217 km2","Weak signal population reached":"932612 pop","Strong signal population reached":"624625 pop","Landcover used":"Yes","Two rays method used":"No","User ID":"farmradio","Radio coverage ID":"NAUTELCD3C95A8D61_2","Generated on":"8/9/2016 10:20:45 PM","ISO_A3":"TZA","desc":"This is the transmitter for Mwambao FM Tanga Tanzania","group":"CIDA3","zoom":13,"stationname":"Mwambao FM"}},
{"type":"Feature","geometry":{"type":"Point","coordinates":[34.822857,-4.839881]},"properties":{"Country":"Tanzania","FormalCountryName":"United Republic of Tanzania","CountrySort":"Tanzania","AfricaRegion":"Eastern Africa","Description":"Radio Standard FM","TX":"2 KW","RX":"Custom","Frequency":"90.1 MHz","Base Name":"Radio Standard FM","Latitude":"04° 50' 23.57\"S","Longitude":"034° 49' 22.29\"E","UTM (WGS84)":"36M E702154 S9464764","Elevation":"1644","Base Ant. Height":"45","Base Ant. Gain":"26.6","Mobile Ant. Height":"5.0 m","Tx Power":"2000","Tx Line Loss":"0.3","Weak signal field":"48.0 dBμV/m","Strong signal field":"60.0 dBμV/m","Weak signal covered area":"39894 km2","Strong signal covered area":"14639 km2","Weak signal population reached":"1541953 pop","Strong signal population reached":"630162 pop","Landcover used":"Yes","Two rays method used":"No","User ID":"farmradio","Radio coverage ID":"NAUTELBF9461FDD5EA_1","Generated on":"8/9/2016 10:22:47 PM","ISO_A3":"TZA","desc":"This is the transmitter site of Radio Standard Singida","group":"OFSP_TZ","zoom":14,"stationname":"Radio Standard FM"}},
{"type":"Feature","geometry":{"type":"Point","coordinates":[33.41666667,-8.5833333]},"properties":{"Country":"Tanzania","FormalCountryName":"United Republic of Tanzania","CountrySort":"Tanzania","AfricaRegion":"Eastern Africa","Description":"Bomba FM Coverage Plot","TX":"2.295 KW","RX":"Custom","Frequency":"104 MHz","Base Name":"Bomba FM (Tanzania)","Latitude":"08° 34' 60.00\"S","Longitude":"033° 25' 00.00\"E","UTM (WGS84)":"36L E545849 S9051188","Elevation":"1511","Base Ant. Height":"60","Base Ant. Gain":"8.8","Mobile Ant. Height":"5.0 m","Tx Power":"2295","Tx Line Loss":"0.3","Weak signal field":"48.0 dBμV/m","Strong signal field":"60.0 dBμV/m","Weak signal covered area":"9731 km2","Strong signal covered area":"4329 km2","Weak signal population reached":"287263 pop","Strong signal population reached":"107578 pop","Landcover used":"Yes","Two rays method used":"No","User ID":"farmradio","Radio coverage ID":"NAUTEL84F371778A52_1","Generated on":"8/9/2016 10:23:08 PM","ISO_A3":"TZA","desc":"This is the transmitter site for Bomba FM in Mbeya","group":"AGRA_Tanzania","zoom":15,"stationname":"Bomba FM (Tanzania)"}},
{"type":"Feature","geometry":{"type":"Point","coordinates":[33.41666667,-8.5833333]},"properties":{"Country":"Tanzania","FormalCountryName":"United Republic of Tanzania","CountrySort":"Tanzania","AfricaRegion":"Eastern Africa","Description":"Bomba FM 120","TX":"2.295 KW","RX":"Custom","Frequency":"104 MHz","Base Name":"Bomba FM (Tanzania)","Latitude":"08° 34' 60.00\"S","Longitude":"033° 25' 00.00\"E","UTM (WGS84)":"36L E545849 S9051188","Elevation":"1511","Base Ant. Height":"120","Base Ant. Gain":"8.8","Mobile Ant. Height":"5.0 m","Tx Power":"2295","Tx Line Loss":"0.3","Weak signal field":"48.0 dBμV/m","Strong signal field":"60.0 dBμV/m","Weak signal covered area":"13341 km2","Strong signal covered area":"6465 km2","Weak signal population reached":"388070 pop","Strong signal population reached":"142241 pop","Landcover used":"Yes","Two rays method used":"No","User ID":"farmradio","Radio coverage ID":"NAUTEL5CDA6A41D5_1","Generated on":"8/9/2016 10:23:11 PM","ISO_A3":"TZA","desc":"This is the transmitter site for Bomba FM in Mbeya","group":"AGRA_Tanzania","zoom":15,"stationname":"Bomba FM (Tanzania)"}},
{"type":"Feature","geometry":{"type":"Point","coordinates":[33.51805556,-8.8513889]},"properties":{"Country":"Tanzania","FormalCountryName":"United Republic of Tanzania","CountrySort":"Tanzania","AfricaRegion":"Eastern Africa","Description":"Baraka FM Coverage","TX":"1.5 KW","RX":"Custom","Frequency":"107.6 MHz","Base Name":"Baraka FM (Tanzania)","Latitude":"08° 51' 05.00\"S","Longitude":"033° 31' 05.00\"E","UTM (WGS84)":"36L E556965 S9021538","Elevation":"2355","Base Ant. Height":"60","Base Ant. Gain":"32.6","Mobile Ant. Height":"5.0 m","Tx Power":"1500","Tx Line Loss":"0.3","Weak signal field":"48.0 dBμV/m","Strong signal field":"60.0 dBμV/m","Weak signal covered area":"94333 km2","Strong signal covered area":"45641 km2","Weak signal population reached":"2879206 pop","Strong signal population reached":"1812128 pop","Landcover used":"Yes","Two rays method used":"No","User ID":"farmradio","Radio coverage ID":"NAUTEL5CDA6A41D5_2","Generated on":"8/9/2016 10:23:12 PM","ISO_A3":"TZA","desc":"This is Baraka FM Transmitter in Mbeya","group":"Agra_Tz","zoom":15,"stationname":"Baraka FM (Tanzania)"}},
{"type":"Feature","geometry":{"type":"Point","coordinates":[33.41666667,-8.5833333]},"properties":{"Country":"Tanzania","FormalCountryName":"United Republic of Tanzania","CountrySort":"Tanzania","AfricaRegion":"Eastern Africa","Description":"Bomba FM larger gain","TX":"2.295 KW","RX":"Custom","Frequency":"104 MHz","Base Name":"Bomba FM (Tanzania)","Latitude":"08° 34' 60.00\"S","Longitude":"033° 25' 00.00\"E","UTM (WGS84)":"36L E545849 S9051188","Elevation":"1511","Base Ant. Height":"60","Base Ant. Gain":"32.6","Mobile Ant. Height":"5.0 m","Tx Power":"2295","Tx Line Loss":"0.3","Weak signal field":"48.0 dBμV/m","Strong signal field":"60.0 dBμV/m","Weak signal covered area":"48511 km2","Strong signal covered area":"22166 km2","Weak signal population reached":"1673854 pop","Strong signal population reached":"863721 pop","Landcover used":"Yes","Two rays method used":"No","User ID":"farmradio","Radio coverage ID":"NAUTEL5CDA6A41D5_3","Generated on":"8/9/2016 10:23:11 PM","ISO_A3":"TZA","desc":"This is the transmitter site for Bomba FM in Mbeya","group":"AGRA_Tanzania","zoom":15,"stationname":"Bomba FM (Tanzania)"}},
{"type":"Feature","geometry":{"type":"Point","coordinates":[33.41666667,-8.5833333]},"properties":{"Country":"Tanzania","FormalCountryName":"United Republic of Tanzania","CountrySort":"Tanzania","AfricaRegion":"Eastern Africa","Description":"Bomba FM 120","TX":"2.295 KW","RX":"Custom","Frequency":"104 MHz","Base Name":"Bomba FM (Tanzania)","Latitude":"08° 34' 60.00\"S","Longitude":"033° 25' 00.00\"E","UTM (WGS84)":"36L E545849 S9051188","Elevation":"1511","Base Ant. Height":"120","Base Ant. Gain":"8.8","Mobile Ant. Height":"5.0 m","Tx Power":"2295","Tx Line Loss":"0.3","Weak signal field":"48.0 dBμV/m","Strong signal field":"60.0 dBμV/m","Weak signal covered area":"13341 km2","Strong signal covered area":"6465 km2","Weak signal population reached":"388070 pop","Strong signal population reached":"142241 pop","Landcover used":"Yes","Two rays method used":"No","User ID":"farmradio","Radio coverage ID":"NAUTEL5CDA6A41D5_1","Generated on":"8/9/2016 10:23:11 PM","ISO_A3":"TZA","desc":"This is the transmitter site for Bomba FM in Mbeya","group":"AGRA_Tanzania","zoom":15,"stationname":"Bomba FM (Tanzania)"}},
{"type":"Feature","geometry":{"type":"Point","coordinates":[33.51805556,-8.8513889]},"properties":{"Country":"Tanzania","FormalCountryName":"United Republic of Tanzania","CountrySort":"Tanzania","AfricaRegion":"Eastern Africa","Description":"Baraka FM Coverage","TX":"1.5 KW","RX":"Custom","Frequency":"107.6 MHz","Base Name":"Baraka FM (Tanzania)","Latitude":"08° 51' 05.00\"S","Longitude":"033° 31' 05.00\"E","UTM (WGS84)":"36L E556965 S9021538","Elevation":"2355","Base Ant. Height":"60","Base Ant. Gain":"32.6","Mobile Ant. Height":"5.0 m","Tx Power":"1500","Tx Line Loss":"0.3","Weak signal field":"48.0 dBμV/m","Strong signal field":"60.0 dBμV/m","Weak signal covered area":"94333 km2","Strong signal covered area":"45641 km2","Weak signal population reached":"2879206 pop","Strong signal population reached":"1812128 pop","Landcover used":"Yes","Two rays method used":"No","User ID":"farmradio","Radio coverage ID":"NAUTEL5CDA6A41D5_2","Generated on":"8/9/2016 10:23:12 PM","ISO_A3":"TZA","desc":"This is Baraka FM Transmitter in Mbeya","group":"Agra_Tz","zoom":15,"stationname":"Baraka FM (Tanzania)"}},
{"type":"Feature","geometry":{"type":"Point","coordinates":[36.7325,-3.344167]},"properties":{"Country":"Tanzania","FormalCountryName":"United Republic of Tanzania","CountrySort":"Tanzania","AfricaRegion":"Eastern Africa","Description":"Radio Habari Maalum","TX":"1 KW FM w/ 4 bay antenna","RX":"Custom","Frequency":"97.7 MHz","Base Name":"Habari Maalum Arusha","Latitude":"03° 20' 39.00\"S","Longitude":"036° 43' 57.00\"E","UTM (WGS84)":"37M E248045 S9630074","Elevation":"1957","Base Ant. Height":"72","Base Ant. Gain":"5.4","Mobile Ant. Height":"5.0 m","Tx Power":"1000","Tx Line Loss":"0.9","Weak signal field":"48.0 dBμV/m","Strong signal field":"60.0 dBμV/m","Weak signal covered area":"16479 km2","Strong signal covered area":"11187 km2","Weak signal population reached":"1343029 pop","Strong signal population reached":"1087915 pop","Landcover used":"Yes","Two rays method used":"No","User ID":"farmradio","Radio coverage ID":"NAUTELC66971C7DFF8_1","Generated on":"8/9/2016 10:23:14 PM","ISO_A3":"TZA","desc":"This is Habari Maalum Transmitter in Arusha","group":"General","zoom":15,"stationname":"Habari Maalum Arusha"}},
{"type":"Feature","geometry":{"type":"Point","coordinates":[39.0667,-6.9]},"properties":{"Country":"Tanzania","FormalCountryName":"United Republic of Tanzania","CountrySort":"Tanzania","AfricaRegion":"Eastern Africa","Description":"Uhuru FM - Tanzania","TX":"3 KW","RX":"Custom","Frequency":"95.7 MHz","Base Name":"Uhuru FM Transmitter","Latitude":"06° 54' 00.00\"S","Longitude":"039° 04' 00.12\"E","UTM (WGS84)":"37M E507369 S9237305","Elevation":"220.4","Base Ant. Height":"144","Base Ant. Gain":"12","Mobile Ant. Height":"5.0 m","Tx Power":"3000","Tx Line Loss":"0.3","Weak signal field":"48.0 dBμV/m","Strong signal field":"60.0 dBμV/m","Weak signal covered area":"33589 km2","Strong signal covered area":"17241 km2","Weak signal population reached":"3760496 pop","Strong signal population reached":"3081308 pop","Landcover used":"Yes","Two rays method used":"No","User ID":"farmradio","Radio coverage ID":"NAUTEL350755D4098_2","Generated on":"8/9/2016 10:23:30 PM","ISO_A3":"TZA","desc":"This is the transmitter for Uhuru FM (IFAD)","group":"IFAD","zoom":14,"stationname":"Uhuru FM Transmitter"}}
]}